scrntime.py
scrntime-1.4.2.dist-info/licenses/LICENSE
scrntime-1.4.2.dist-info/METADATA
scrntime-1.4.2.dist-info/WHEEL
scrntime-1.4.2.dist-info/entry_points.txt
scrntime-1.4.2.dist-info/top_level.txt
scrntime-1.4.2.dist-info/RECORD
