Metadata-Version: 2.4
Name: scrntime
Version: 1.4.2
Summary: A CLI for displaying daily screentime with afk/idle time support
Home-page: https://github.com/sahaj-b/scrntime.git
Author: Sahaj Bhatt
Author-email: sahajb0606@gmail.com
License: BSD
Classifier: Programming Language :: Python :: 3
Classifier: License :: OSI Approved :: BSD License
Classifier: Operating System :: POSIX :: Linux
License-File: LICENSE
Dynamic: author
Dynamic: author-email
Dynamic: classifier
Dynamic: home-page
Dynamic: license
Dynamic: license-file
Dynamic: summary
